LICENSE
README.md
setup.py
capys.egg-info/PKG-INFO
capys.egg-info/SOURCES.txt
capys.egg-info/dependency_links.txt
capys.egg-info/requires.txt
capys.egg-info/top_level.txt
psearcherr/BaiduEngine.py
psearcherr/BaseEngine.py
psearcherr/BingEngine.py
psearcherr/__init__.py