Metadata-Version: 2.1
Name: capys
Version: 0.0.1
Summary: Capybara, an object FFI/RPC tool like PyOdide, PyJnius, or Luajava with Jupyter/Qt UI&DevTools
Home-page: https://github.com/duangsuse-valid-projects/Share
Author: duangsuse
Author-email: fedora-opensuse@outlook.com
License: MIT
Classifier: Programming Language :: Python :: 3
Classifier: License :: OSI Approved :: MIT License
Classifier: Operating System :: OS Independent
License-File: LICENSE
